{
  "$schema": "https://claudius.to/theme.json",
  "name": "Undertale",
  "id": "undertale",
  "light": {
    "seeds": {
      "neutral": "#909090",
      "primary": "#FF0000",
      "success": "#00FF00",
      "warning": "#FFFF00",
      "error": "#FF3333",
      "info": "#00FFFF",
      "interactive": "#0000FF",
      "diffAdd": "#00FF00",
      "diffDelete": "#FF3333"
    }
  },
  "dark": {
    "seeds": {
      "neutral": "#909090",
      "primary": "#FF0000",
      "success": "#00FF00",
      "warning": "#FFC90E",
      "error": "#FF3333",
      "info": "#00FFFF",
      "interactive": "#00BFFF",
      "diffAdd": "#00FF00",
      "diffDelete": "#FF3333"
    }
  }
}
